subprocess_multipipe/README.MD
subprocess_multipipe/__init__.py
subprocess_multipipe/requirements.txt
subprocess_multipipe/run_multipipe_subproc.py
subprocess_multipipe/start_pipethread.py
subprocess_multipipe/thirdparty.json
subprocess_multipipe-0.10.dist-info/LICENSE.rst
subprocess_multipipe-0.10.dist-info/METADATA
subprocess_multipipe-0.10.dist-info/WHEEL
subprocess_multipipe-0.10.dist-info/top_level.txt
subprocess_multipipe-0.10.dist-info/RECORD
