Metadata-Version: 2.1
Name: subprocess-multipipe
Version: 0.10
Summary: Uses subprocess.stdin.write and named pipes (Windows) to read data from / write data to a subprocess
Home-page: https://github.com/hansalemaos/subprocess_multipipe
Author: Johannes Fischer
Author-email: aulasparticularesdealemaosp@gmail.com
License: MIT
Keywords: pickle,unpickle,subprocess
Classifier: Development Status :: 4 - Beta
Classifier: Programming Language :: Python :: 3 :: Only
Classifier: Programming Language :: Python :: 3.10
Classifier: Topic :: Software Development :: Libraries :: Python Modules
Classifier: Topic :: Utilities
License-File: LICENSE.rst
Requires-Dist: hackyargparser
Requires-Dist: kthread
Requires-Dist: kthread-sleep
Requires-Dist: pywinpipe
Requires-Dist: subprocess-alive
Requires-Dist: varpickler
